ansys/fluent/core/__init__.py
ansys/fluent/core/data_model_cache.py
ansys/fluent/core/exceptions.py
ansys/fluent/core/field_data_interfaces.py
ansys/fluent/core/file_session.py
ansys/fluent/core/fluent_connection.py
ansys/fluent/core/get_build_details.py
ansys/fluent/core/journaling.py
ansys/fluent/core/logger.py
ansys/fluent/core/logging_config.yaml
ansys/fluent/core/module_config.py
ansys/fluent/core/parametric.py
ansys/fluent/core/pyfluent_warnings.py
ansys/fluent/core/report.py
ansys/fluent/core/rpvars.py
ansys/fluent/core/search.py
ansys/fluent/core/session.py
ansys/fluent/core/session_base_meshing.py
ansys/fluent/core/session_meshing.py
ansys/fluent/core/session_meshing.pyi
ansys/fluent/core/session_pure_meshing.py
ansys/fluent/core/session_pure_meshing.pyi
ansys/fluent/core/session_shared.py
ansys/fluent/core/session_solver.py
ansys/fluent/core/session_solver.pyi
ansys/fluent/core/session_solver_aero.py
ansys/fluent/core/session_solver_icing.py
ansys/fluent/core/session_solver_lite.py
ansys/fluent/core/session_utilities.py
ansys/fluent/core/system_coupling.py
ansys/fluent/core/workflow.py
ansys/fluent/core/_stand_alone_datamodel_client/_datamodel_client.py
ansys/fluent/core/codegen/__init__.py
ansys/fluent/core/codegen/allapigen.py
ansys/fluent/core/codegen/builtin_settingsgen.py
ansys/fluent/core/codegen/datamodelgen.py
ansys/fluent/core/codegen/print_fluent_version.py
ansys/fluent/core/codegen/settingsgen.py
ansys/fluent/core/codegen/tuigen.py
ansys/fluent/core/codegen/walk_api.py
ansys/fluent/core/codegen/write_settings_yaml.py
ansys/fluent/core/codegen/data/__init__.py
ansys/fluent/core/codegen/data/fluent_gui_help_patch.py
ansys/fluent/core/codegen/data/meshing_utilities_examples.py
ansys/fluent/core/codegen/data/static_info_222_meshing.pickle
ansys/fluent/core/codegen/data/static_info_222_solver.pickle
ansys/fluent/core/docker/docker_compose.py
ansys/fluent/core/docker/utils.py
ansys/fluent/core/docs/.gitignore
ansys/fluent/core/examples/__init__.py
ansys_fluent_core-0.35.0.dist-info/licenses/LICENSE
ansys_fluent_core-0.35.0.dist-info/WHEEL
ansys_fluent_core-0.35.0.dist-info/METADATA
ansys_fluent_core-0.35.0.dist-info/RECORD
