Metadata-Version: 2.4
Name: ansys-fluent-core
Version: 0.35.0
Summary: PyFluent provides Pythonic access to Ansys Fluent.
Author-email: "ANSYS, Inc." <pyansys.core@ansys.com>
Maintainer-email: "ANSYS, Inc." <pyansys.core@ansys.com>
Requires-Python: >=3.10,<3.14
Classifier: Development Status :: 4 - Beta
Classifier: Programming Language :: Python :: 3
Classifier: License :: OSI Approved :: MIT License
Classifier: Operating System :: OS Independent
License-File: LICENSE
Requires-Dist: ansys-api-fluent>=0.3.36
Requires-Dist: ansys-platform-instancemanagement~=1.1
Requires-Dist: ansys-tools-filetransfer>=0.1,<0.3
Requires-Dist: ansys-units>=0.7.0,<1.0
Requires-Dist: defusedxml>=0.7.1
Requires-Dist: deprecated>=1.2.18
Requires-Dist: docker>=7.1.0
Requires-Dist: grpcio>=1.30.0
Requires-Dist: grpcio-health-checking>=1.30.0
Requires-Dist: grpcio-status>=1.26.0
Requires-Dist: nltk>=3.9.1
Requires-Dist: numpy>=1.14.0,<3.0.0
Requires-Dist: pandas>=1.1.0,<3.0.0
Requires-Dist: pyansys-tools-report>=0.8.1
Requires-Dist: pyyaml>=6.0
Requires-Dist: Sphinx==8.1.3 ; extra == "docs"
Requires-Dist: jupyter_sphinx==0.5.3 ; extra == "docs"
Requires-Dist: numpydoc==1.9.0 ; extra == "docs"
Requires-Dist: matplotlib==3.10.5 ; extra == "docs"
Requires-Dist: ansys-sphinx-theme==1.5.3 ; extra == "docs"
Requires-Dist: pypandoc==1.15 ; extra == "docs"
Requires-Dist: pytest-sphinx==0.6.3 ; extra == "docs"
Requires-Dist: sphinx-autobuild==2024.10.3 ; extra == "docs"
Requires-Dist: sphinx-autodoc-typehints==3.0.1 ; extra == "docs"
Requires-Dist: sphinx-copybutton==0.5.2 ; extra == "docs"
Requires-Dist: sphinx-gallery==0.19.0 ; extra == "docs"
Requires-Dist: sphinx-notfound-page==1.1.0 ; extra == "docs"
Requires-Dist: sphinxcontrib-websupport==2.0.0 ; extra == "docs"
Requires-Dist: sphinxemoji==0.3.1 ; extra == "docs"
Requires-Dist: sphinx-toggleprompt==0.6.0 ; extra == "docs"
Requires-Dist: autodocsumm==0.2.14 ; extra == "docs"
Requires-Dist: beautifulsoup4==4.13.4 ; extra == "docs"
Requires-Dist: openpyxl>=3.1.5 ; extra == "docs"
Requires-Dist: plotly>=5.22.0 ; extra == "docs"
Requires-Dist: python-pptx>=0.6.23 ; extra == "docs"
Requires-Dist: quarto-cli==1.7.32 ; extra == "docs"
Requires-Dist: pdf2image==1.17.0 ; extra == "docs"
Requires-Dist: seaborn>=0.13.2 ; extra == "docs"
Requires-Dist: h5py==3.14.0 ; extra == "reader"
Requires-Dist: pytest==8.4.1 ; extra == "tests"
Requires-Dist: pytest-cov==6.2.1 ; extra == "tests"
Requires-Dist: pytest-mock==3.14.1 ; extra == "tests"
Requires-Dist: pytest-xdist==3.8.0 ; extra == "tests"
Requires-Dist: pyfakefs==5.9.2 ; extra == "tests"
Project-URL: Documentation, https://fluent.docs.pyansys.com/
Project-URL: Source, https://github.com/ansys/pyfluent
Project-URL: Tracker, https://github.com/ansys/pyfluent/issues
Provides-Extra: docs
Provides-Extra: reader
Provides-Extra: tests
